Metadata-Version: 2.1
Name: IPAM-PACMan
Version: 1.0.0
Summary: PACMan: An chlorophyll-a fluorometry automation software designed for Walz (GMBH) Microscopy IPAM.
Project-URL: Homepage, https://pypi.org/project/IPAM-PACMan
Project-URL: Github, https://github.com/OllePonten/PACMan
Project-URL: Bug Tracker, https://github.com/OllePonten/PACMan/issues
Author-email: Olle Pontén <olle.ponten@gmail.com>
License-Expression: GPL-3.0-or-later
License-File: LICENSE
Classifier: License :: OSI Approved :: GNU General Public License v3 or later (GPLv3+)
Classifier: Operating System :: Microsoft :: Windows :: Windows 7
Classifier: Operating System :: Microsoft :: Windows :: Windows 10
Classifier: Programming Language :: Python :: 3
Requires-Python: >=3.9
Requires-Dist: comtypes>=1.1
Requires-Dist: matplotlib>=3.5
Requires-Dist: msvc-runtime
Requires-Dist: numpy>=1.20
Requires-Dist: opencv-python>=4.2
Requires-Dist: psutil>=5.0.0
Requires-Dist: pyserial>=3.5
Requires-Dist: scikit-image>=0.18
Requires-Dist: scipy>=1.8
Requires-Dist: tifffile>=2021
